{"avg_augmented_recommended_ratio": 0.0, "avg_augmented_required_ratio": 0.0, "avg_recommended_score_ratio": 0.2, "avg_required_ratio": 0.54, "required_fields": {"name": 1.0, "description": 0.83, "author": 0.0, "url": 1.0, "measurementTechnique": 0.0, "includedInDataCatalog": 1.0, "distribution": 0.0, "funding": 0.01, "date": 1.0}, "recommended_fields": {"dateCreated": 0.0, "dateModified": 1.0, "datePublished": 1.0, "citedBy": 0.0, "doi": 0.0, "infectiousAgent": 0.0, "healthCondition": 0.0, "species": 0.0, "variableMeasured": 0.0, "citation": 0.03, "conditionsOfAccess": 0.0, "isBasedOn": 0.0, "keywords": 0.4, "license": 0.83, "sdPublisher": 0.0, "spatialCoverage": 0.0, "temporalCoverage": 0.0, "topicCategory": 0.0, "identifier": 0.0, "usageInfo": 0.0, "interactionStatistic": 0.96}, "sum_required_coverage": 4.84, "sum_recommended_coverage": 4.22}